armorblox/__init__.py
armorblox/api/__init__.py
armorblox/api/base_api.py
armorblox/api/incidents_api.py
armorblox/client.py
armorblox/config.py
armorblox_sdk-0.1.4.dist-info/LICENSE
armorblox_sdk-0.1.4.dist-info/WHEEL
armorblox_sdk-0.1.4.dist-info/METADATA
armorblox_sdk-0.1.4.dist-info/RECORD
