Metadata-Version: 2.1
Name: armorblox-sdk
Version: 0.1.4
Summary: Armorblox SDK for Python
Home-page: https://github.com/armorblox/armorblox-python-sdk
License: Apache-2.0
Author: Rajat Upadhyaya
Author-email: 45485+urajat@users.noreply.github.com
Requires-Python: >=3.8,<4.0
Classifier: Development Status :: 3 - Alpha
Classifier: Intended Audience :: Developers
Classifier: License :: OSI Approved :: Apache Software License
Classifier: Operating System :: OS Independent
Classifier: Programming Language :: Python
Classifier: Programming Language :: Python :: 3
Classifier: Programming Language :: Python :: 3.10
Classifier: Programming Language :: Python :: 3.8
Classifier: Programming Language :: Python :: 3.9
Classifier: Topic :: Security
Classifier: Topic :: Software Development :: Libraries :: Python Modules
Requires-Dist: cached-property (>=1.5.2,<2.0.0)
Requires-Dist: requests (>=2.27.1,<3.0.0)
Project-URL: Repository, https://github.com/armorblox/armorblox-python-sdk
